<?xml version="1.0" encoding="utf-8"?>
<!-- Copyright 2018 Xavier Piernas <xavier.piernas@qubiq.es>
     License AGPL-3.0 or later (https://www.gnu.org/licenses/agpl). -->
<odoo>
    <record id="product_category_contracts_form" model="ir.ui.view">
        <field name="name">product.category.contracts.form</field>
        <field name="model">product.category</field>
        <field name="inherit_id" ref="project_contracts.product_category_contracts_form"/>
        <field name="arch" type="xml">
            <xpath expr="//field[@name='contract_hours']" position="after">
                <field name="show_hours_report"/>
            </xpath>
        </field>
    </record>
</odoo>